helloconfig/__init__.py
helloconfig/config_bases.py
helloconfig/exceptions.py
helloconfig/immutable.py
helloconfig/parsers.py
helloconfig-0.1.0.post1.dist-info/LICENSE
helloconfig-0.1.0.post1.dist-info/METADATA
helloconfig-0.1.0.post1.dist-info/WHEEL
helloconfig-0.1.0.post1.dist-info/top_level.txt
helloconfig-0.1.0.post1.dist-info/RECORD
