Metadata-Version: 2.1
Name: helloconfig
Version: 0.1.0.post1
Summary: Describe config, i'll create it
Author-email: Elchin Sarkarov <elchin751@gmail.com>
Project-URL: Homepage, https://github.com/elchinchel/hello-config
Project-URL: Bug Tracker, https://github.com/elchinchel/hello-config/issues
Classifier: Development Status :: 4 - Beta
Classifier: Programming Language :: Python :: 3
Classifier: License :: OSI Approved :: Apache Software License
Classifier: Operating System :: POSIX
Classifier: Operating System :: Microsoft :: Windows
Requires-Python: >=3.7
License-File: LICENSE
Requires-Dist: dataclass-factory
Requires-Dist: pyyaml
Provides-Extra: test
Requires-Dist: pytest ; extra == 'test'
Requires-Dist: pytest-cov ; extra == 'test'
